cm2py/__init__.py
cm2py/cm2py.py
cm2py/utilities/__init__.py
cm2py/utilities/utilities.py
cm2py-0.3.11.dist-info/LICENSE
cm2py-0.3.11.dist-info/METADATA
cm2py-0.3.11.dist-info/WHEEL
cm2py-0.3.11.dist-info/top_level.txt
cm2py-0.3.11.dist-info/RECORD
