Metadata-Version: 2.2
Name: cm2py
Version: 0.3.11
Summary: Circuit Maker 2 save generation and manipulation package
Author-email: SKM GEEK <qestudios17@gmail.com>
License: The MIT License (MIT)
Project-URL: Homepage, https://github.com/QEStudios/cm2py
Project-URL: Bug Tracker, https://github.com/QEStudios/cm2py/issues
Classifier: Programming Language :: Python :: 3
Classifier: License :: OSI Approved :: MIT License
Classifier: Operating System :: OS Independent
Requires-Python: >=3.7
License-File: LICENSE
Requires-Dist: uuid
Requires-Dist: regex
